md2reveal/__init__.py
md2reveal/cmdline.py
md2reveal/md.py
md2reveal/reveal.py
md2reveal/template.html
md2reveal-1.2.0.dist-info/METADATA
md2reveal-1.2.0.dist-info/WHEEL
md2reveal-1.2.0.dist-info/entry_points.txt
md2reveal-1.2.0.dist-info/top_level.txt
md2reveal-1.2.0.dist-info/RECORD
