Metadata-Version: 2.1
Name: md2reveal
Version: 1.2.0
Summary: Converting markdown to reveal.js html page
Home-page: https://github.com/LKI/md2reveal
Author: Lirian Su
Author-email: liriansu@gmail.com
License: WTFPL
Platform: UNKNOWN
